readsettings/__init__.py
readsettings-3.4.5.dist-info/LICENSE
readsettings-3.4.5.dist-info/METADATA
readsettings-3.4.5.dist-info/WHEEL
readsettings-3.4.5.dist-info/top_level.txt
readsettings-3.4.5.dist-info/RECORD
