Metadata-Version: 2.1
Name: readsettings
Version: 3.4.5
Summary: Easily manage a customized settings file in JSON, YML, YAML or TOML which you can use for storing all of the settings for your application.
Home-page: https://github.com/Richienb/readsettings-python
Author: Richie Bendall
Author-email: richiebendall@gmail.com
License: UNKNOWN
Platform: UNKNOWN
Classifier: Development Status :: 6 - Mature
Classifier: Intended Audience :: Developers
Classifier: License :: OSI Approved :: MIT License
Classifier: Natural Language :: English
Classifier: Programming Language :: Python
Classifier: Operating System :: OS Independent
Classifier: Topic :: Software Development :: Libraries :: Python Modules
